premier_league/__init__.py
premier_league/base.py
premier_league/api/__init__.py
premier_league/api/app.py
premier_league/api/config/__init__.py
premier_league/api/config/config.py
premier_league/api/routes/__init__.py
premier_league/api/routes/players.py
premier_league/api/routes/ranking.py
premier_league/api/routes/transfer.py
premier_league/api/services/__init__.py
premier_league/api/services/player_service.py
premier_league/api/services/ranking_service.py
premier_league/api/services/transfer_service.py
premier_league/api/utils/__init__.py
premier_league/api/utils/decorator.py
premier_league/data/__init__.py
premier_league/data/initialize.py
premier_league/data/premier_league.sql
premier_league/data/models/__init__.py
premier_league/data/models/base.py
premier_league/data/models/game.py
premier_league/data/models/game_stats.py
premier_league/data/models/league.py
premier_league/data/models/team.py
premier_league/lambda_functions/__init__.py
premier_league/lambda_functions/deploy_premier_league.py
premier_league/lambda_functions/requirements.txt
premier_league/lambda_functions/serverless.yml
premier_league/lambda_functions/src/__init__.py
premier_league/lambda_functions/src/player_lambda.py
premier_league/lambda_functions/src/ranking_lambda.py
premier_league/lambda_functions/src/transfers_lambda.py
premier_league/lambda_functions/src/utils/__init__.py
premier_league/lambda_functions/src/utils/methods.py
premier_league/match_statistics/__init__.py
premier_league/match_statistics/match_statistics.py
premier_league/players/__init__.py
premier_league/players/season_leaders.py
premier_league/ranking/__init__.py
premier_league/ranking/ranking_table.py
premier_league/transfers/__init__.py
premier_league/transfers/transfers.py
premier_league/utils/__init__.py
premier_league/utils/methods.py
premier_league/utils/threading.py
premier_league/utils/url.py
premier_league/utils/xpath.py
premier_league-1.0.4.dist-info/licenses/LICENSE.md
premier_league-1.0.4.dist-info/METADATA
premier_league-1.0.4.dist-info/WHEEL
premier_league-1.0.4.dist-info/top_level.txt
premier_league-1.0.4.dist-info/RECORD
