Metadata-Version: 2.4
Name: premier_league
Version: 1.0.4
Summary: Premier League Data Analysis Package
Author: Michael Li
Requires-Python: >=3.9
License-File: LICENSE.md
Requires-Dist: requests==2.28.1
Requires-Dist: requests-cache==1.2.1
Requires-Dist: lxml==5.3.1
Requires-Dist: beautifulsoup4==4.12.3
Requires-Dist: prettytable==3.11.0
Requires-Dist: PyYAML==6.0.2
Requires-Dist: pandas==2.2.3
Requires-Dist: tqdm==4.67.1
Requires-Dist: SQLAlchemy==2.0.38
Requires-Dist: appdirs==1.4.4
Provides-Extra: pdf
Requires-Dist: reportlab==4.0.4; extra == "pdf"
Provides-Extra: api
Requires-Dist: flask==3.0.0; extra == "api"
Requires-Dist: flask-caching==2.3.0; extra == "api"
Requires-Dist: flask-cors==5.0.0; extra == "api"
Requires-Dist: flask-limiter==3.11; extra == "api"
Requires-Dist: gunicorn==23.0.0; extra == "api"
Provides-Extra: lambda
Requires-Dist: boto3==1.37.18; extra == "lambda"
Provides-Extra: all
Requires-Dist: boto3==1.37.18; extra == "all"
Requires-Dist: flask-cors==5.0.0; extra == "all"
Requires-Dist: flask-caching==2.3.0; extra == "all"
Requires-Dist: gunicorn==23.0.0; extra == "all"
Requires-Dist: flask-limiter==3.11; extra == "all"
Requires-Dist: reportlab==4.0.4; extra == "all"
Requires-Dist: flask==3.0.0; extra == "all"
Dynamic: author
Dynamic: description
Dynamic: description-content-type
Dynamic: license-file
Dynamic: provides-extra
Dynamic: requires-dist
Dynamic: requires-python
Dynamic: summary
